{
    "auto": {
        "new": true,
        "id": "3012",
        "brand": "Toyota",
        "model": "Camry",
        "generation": "2023-02-17",
        "year": "2023-02-17",
        "modification": "2.0 6АТ (150 л.с.)",
        "price": 1990000,
        "credit_from": 43260,
        "power": "150",
        "fuel_consumption": "5.5",
        "max_speed": "210",
        "acceleration": "11",
        "transmission": "Автоматическая",
        "drive_unit": "Передний",
        "body_type": "неизвестно",
        "volume": "2.0",
        "engine_type": "Бензиновый",
        "secure": [
            "Антиблокировочная система (ABS)",
            "Система распределения тормозного усилия (EBD)",
            "Усилитель экстренного торможения (BAS)",
            "Антипробуксовочная система (TRC)",
            "Система курсовой устойчивости (VSC+)",
            "Система помощи при подъеме по склону (HAC)",
            "Конструкция передних сидений, снижающая вероятность травмы шеи (технология WIL)",
            "Фронтальные и боковые подушки безопасности",
            "Шторки безопасности",
            "Система вызова экстренных оперативных служб «ЭРА-ГЛОНАСС»",
            "Крепление ISOFIX для детских автокресел",
            "Набор автомобилиста"
        ],
        "exterior": [
            "Светодиодные фары ближнего и дальнего света",
            "Светодиодные дневные ходовые огни",
            "Светодиодные передние противотуманные фары",
            "Антенна «Плавник акулы»",
            "Легкосплавные колесные диски, шины 205/65 R16",
            "Полноразмерное запасное колесо на легкосплавном диске",
            "Ручки дверей, окрашенные в цвет кузова",
            "Нижняя решетка радиатора цвета чёрный металлик"
        ],
        "interior": [],
        "comfort": [
            "Мультифункциональное рулевое колесо",
            "Кожаная (комбинация из натуральной и синтетической кожи) обивка селектора управления трансмиссией",
            "Датчик света",
            "Система мониторинга давления в шинах",
            "Боковые зеркала заднего вида с электрорегулировкой, электроприводом складывания и со светодиодными повторителями указателей поворота",
            "Передние и задние стеклоподъемники с функцией «Auto»",
            "Электромеханический стояночный тормоз с функцией автоматической активации",
            "Регулировка рулевой колонки по вылету и по наклону",
            "Двухзонный климат-контроль",
            "Обивка сидений тканью",
            "Механическая регулировка водительского сиденья в 6 направлениях",
            "Механическая регулировка пассажирского сиденья в 4 направлениях",
            "Сиденья второго ряда, складывающиеся в пропорции 60:40",
            "Цветной многофункциональный дисплей 4.2\" на панели приборов"
        ],
        "multimedia": [
            "USB-разъем для воспроизведения медиафайлов и зарядки мобильных устройств на центральной консоли",
            "2 USB-разъема для зарядки мобильных устройств пассажиров второго ряда",
            "Аудио-разъем (AUX)",
            "Аудиосистема с поддержкой CD/MP3/WMA/AAC",
            "6 динамиков аудиосистемы"
        ],
        "images": [
            "TOYOTA/toyota_camry/camry4326030120.jpg",
            "TOYOTA/toyota_camry/camry4326030121.jpg",
            "TOYOTA/toyota_camry/camry4326030122.jpg",
            "TOYOTA/toyota_camry/camry4326030123.jpg",
            "TOYOTA/toyota_camry/camry4326030124.jpg",
            "TOYOTA/toyota_camry/camry4326030125.jpg"
        ]
    }
}