{
    "auto": {
        "new": true,
        "id": "3315",
        "brand": "Hyundai",
        "model": "Creta",
        "generation": "2023-02-17",
        "year": "2023-02-17",
        "modification": "1.6 6AКП (123 л.с.) FWD",
        "price": 675000,
        "credit_from": 14673,
        "power": "123",
        "fuel_consumption": "5.9",
        "max_speed": "169",
        "acceleration": "12.1",
        "transmission": "Автоматическая",
        "drive_unit": "FDW",
        "body_type": "неизвестно",
        "volume": "1.6",
        "engine_type": "Бензиновый",
        "secure": [
            "Фронтальные подушки безопасности водителя и переднего пассажира",
            "Регулировка передних ремней безопасности по высоте",
            "Преднатяжители передних ремней безопасности",
            "Система управления стабилизацией (ABS, ESP, TCS, EBD, VSM)",
            "Система помощи при старте в гору и спуске с горы (HAC)",
            "Система предупреждения водителей сзади при экстренном торможении (ESS)",
            "Устройство вызова экстренных оперативных служб «ЭРА-ГЛОНАСС»",
            "Система мониторинга давления в шинах",
            "Передние и задние дисковые тормоза"
        ],
        "exterior": [
            "Дневные ходовые огни",
            "Ручки дверей в цвет кузова",
            "Боковые зеркала в цвет кузова",
            "Передние и задние брызговики",
            "Пластиковые накладки на порогах дверей",
            "Антенна на крыше типа \"плавник\"",
            "Стальные диски 16\" с шинами 205/65 R16",
            "Рейлинги на крыше"
        ],
        "interior": [
            "Складывающаяся спинка второго ряда сидений (в пропорции 60:40)",
            "Обивка сидений тканью",
            "Передние и задние подголовники"
        ],
        "comfort": [
            "Электропривод и подогрев наружных зеркал",
            "Маршрутный компьютер",
            "Разъем USB для подключения внешних устройств",
            "Bluetooth/громкая связь Hands Free",
            "Управление аудиосистемой на руле",
            "Передние и задние электростеклоподъемники",
            "Электроусилитель руля",
            "Две розетки 12В на центральной консоли",
            "Зеркальца в солнцезащитных козырьках",
            "Регулировка сиденья водителя по высоте",
            "Футляр для очков в потолочной консоли",
            "Регулировка рулевой колонки по высоте",
            "Шумоизоляция капота",
            "Центральный подлокотник с боксом",
            "Аудиосистема (Радио/MP3) с 4 динамиками",
            "Кондиционер",
            "Трехступенчатый подогрев передних сидений",
            "Пульт управления центральным замком в ключе",
            "Крючки для фиксации груза в багажнике",
            "Дополнительный органайзер под полом багажника",
            "Полка багажника"
        ],
        "multimedia": [],
        "images": [
            "HYUNDAI/Hyundai_Creta/creta1467333150.jpg",
            "HYUNDAI/Hyundai_Creta/creta1467333151.jpg",
            "HYUNDAI/Hyundai_Creta/creta1467333152.jpg",
            "HYUNDAI/Hyundai_Creta/creta1467333153.jpg",
            "HYUNDAI/Hyundai_Creta/creta1467333154.jpg",
            "HYUNDAI/Hyundai_Creta/creta1467333155.jpg",
            "HYUNDAI/Hyundai_Creta/creta1467333156.jpg",
            "HYUNDAI/Hyundai_Creta/creta1467333157.jpg"
        ]
    }
}